keyst_monero_toolkit/__init__.py
keyst_monero_toolkit/cli.py
keyst_monero_toolkit/keys.py
keyst_monero_toolkit-0.1.1.dist-info/METADATA
keyst_monero_toolkit-0.1.1.dist-info/WHEEL
keyst_monero_toolkit-0.1.1.dist-info/entry_points.txt
keyst_monero_toolkit-0.1.1.dist-info/RECORD
